.DS_Store
py2pyadd/__init__.py
py2pyadd-0.0.2.dist-info/LICENSE.txt
py2pyadd-0.0.2.dist-info/METADATA
py2pyadd-0.0.2.dist-info/WHEEL
py2pyadd-0.0.2.dist-info/top_level.txt
py2pyadd-0.0.2.dist-info/RECORD
